Metadata-Version: 2.4
Name: HydroTrace
Version: 0.3
Summary: Hydrogen Trace Analysis Suite
Home-page: https://github.com/majroy/HydroTrace
Author: M J Roy
Author-email: matthew.roy@manchester.ac.uk
License: Creative Commons Attribution-Noncommercial-Share Alike license
Keywords: Hydrogen,Trace,Curve-fit
Classifier: Development Status :: 3 - Alpha
Classifier: Environment :: Win32 (MS Windows)
Classifier: Topic :: Scientific/Engineering :: Visualization
Classifier: License :: OSI Approved :: GNU General Public License v3 or later (GPLv3+)
Classifier: Operating System :: Microsoft :: Windows :: Windows 11
Classifier: Programming Language :: Python :: 3.12
Classifier: Intended Audience :: End Users/Desktop
Classifier: Natural Language :: English
License-File: LICENSE
Requires-Dist: numpy
Requires-Dist: scipy
Requires-Dist: pyyaml>=5.0
Requires-Dist: matplotlib
Requires-Dist: PyQt6>=6.8
Dynamic: author
Dynamic: author-email
Dynamic: classifier
Dynamic: description
Dynamic: home-page
Dynamic: keywords
Dynamic: license
Dynamic: license-file
Dynamic: requires-dist
Dynamic: summary
